julimath/__init__.py
julimath/julimath.py
julimath/utils.py
julimath-0.1.0.dist-info/licenses/LICENSE
julimath-0.1.0.dist-info/METADATA
julimath-0.1.0.dist-info/WHEEL
julimath-0.1.0.dist-info/top_level.txt
julimath-0.1.0.dist-info/RECORD
