Metadata-Version: 2.4
Name: julimath
Version: 0.1.0
Summary: A simple & friendly math library for beginners with auto-input, shortcuts, and helpful logs.
Author-email: Galih Julian <membventra@gmail.com>
License: MIT
Project-URL: Homepage, https://github.com/Enex-kblm/julimath
Keywords: math,beginner,library,julimath
Classifier: Programming Language :: Python :: 3
Classifier: License :: OSI Approved :: MIT License
Classifier: Operating System :: OS Independent
Requires-Python: >=3.7
License-File: LICENSE
Dynamic: license-file
